{
  "$schema": "https://json-schema.org/draft/2020-12/schema",
  "$id": "https://golden-magic.local/schemas/tool-pack.schema.json",
  "title": "Golden Magic Tool Pack",
  "type": "object",
  "additionalProperties": false,
  "required": ["id", "name", "version"],
  "properties": {
    "id": {
      "type": "string",
      "pattern": "^tool\\.[a-z0-9][a-z0-9._-]*$"
    },
    "name": {
      "type": "string",
      "minLength": 1
    },
    "version": {
      "type": "string",
      "pattern": "^[0-9]+$"
    },
    "commands": {
      "type": "array",
      "items": {
        "$ref": "#/$defs/command"
      },
      "default": []
    }
  },
  "$defs": {
    "command": {
      "type": "object",
      "additionalProperties": false,
      "required": ["name"],
      "properties": {
        "name": {
          "type": "string",
          "minLength": 1
        },
        "description": {
          "type": "string"
        },
        "descriptor": {
          "type": "string",
          "pattern": "^[a-z0-9][a-z0-9._-]*$"
        },
        "patterns": {
          "type": "array",
          "items": {
            "type": "string",
            "minLength": 1
          },
          "default": []
        },
        "args": {
          "type": "array",
          "items": {
            "$ref": "#/$defs/arg"
          },
          "default": []
        },
        "subcommands": {
          "type": "array",
          "items": {
            "$ref": "#/$defs/command"
          },
          "default": []
        }
      }
    },
    "arg": {
      "type": "object",
      "additionalProperties": false,
      "required": ["name", "kind"],
      "properties": {
        "name": {
          "type": "string",
          "minLength": 1
        },
        "kind": {
          "type": "string",
          "enum": ["flag", "option", "positional"]
        },
        "patterns": {
          "type": "array",
          "items": {
            "type": "string",
            "minLength": 1
          },
          "default": []
        },
        "affects_output": {
          "type": "boolean",
          "default": false
        }
      }
    }
  }
}
